{
    "cabins": [
        "CabinTest1",
        "CabinTest2",
        "CabinTest3"
    ],
    "cores": [
        "CoreTest1",
        "CoreTest2",
        "CoreTest3",
        "CoreTest4",
        "CoreTest5",
        "CoreTest6",
        "CoreTest7",
        "CoreTest8",
        "CoreTest9",
        "CoreTest10",
        "CoreTest11",
        "CoreTest12",
        "CoreTest13",
        "CoreTest14",
        "CoreTest15",
        "CoreTest16",
        "CoreTest17",
        "CoreTest18",
        "CoreTest19",
        "CoreTest20"
    ],
    "utilities": [
        "UtilityTest1",
        "UtilityTest2"
    ],
    "wings": [
        "WingTest1",
        "WingTest2",
        "WingTest3"
    ],
    "weapons": [
        "GunTest1",
        "GunTest2",
        "GunTest3",
        "GunTest4"
    ]
}